pysmarthome
setup.py
pysmarhome_cli/__init__.py
pysmarhome_cli/action.py
pysmarhome_cli/list.py
pysmarhome_cli/scene.py
pysmarhome_cli/graphql/__init__.py
pysmarhome_cli/graphql/mutations.py
pysmarhome_cli/graphql/queries.py
pysmarhome_cli/graphql/request.py
pysmarthome_cli.egg-info/PKG-INFO
pysmarthome_cli.egg-info/SOURCES.txt
pysmarthome_cli.egg-info/dependency_links.txt
pysmarthome_cli.egg-info/not-zip-safe
pysmarthome_cli.egg-info/requires.txt
pysmarthome_cli.egg-info/top_level.txt