Metadata-Version: 2.1
Name: pysmarthome-cli
Version: 0.0.0
Summary: A command line interface for pysmarthome
Home-page: https://github.com/filipealvesdef/pysmarthome-cli/
Author: Filipe Alves
Author-email: filipe.alvesdefernando@gmail.com
License: UNKNOWN
Platform: UNKNOWN
